keras_preprocessing/__init__.py
keras_preprocessing/sequence.py
keras_preprocessing/text.py
keras_preprocessing/image/__init__.py
keras_preprocessing/image/affine_transformations.py
keras_preprocessing/image/dataframe_iterator.py
keras_preprocessing/image/directory_iterator.py
keras_preprocessing/image/image_data_generator.py
keras_preprocessing/image/iterator.py
keras_preprocessing/image/numpy_array_iterator.py
keras_preprocessing/image/utils.py
Keras_Preprocessing-1.1.1.dist-info/LICENSE
Keras_Preprocessing-1.1.1.dist-info/METADATA
Keras_Preprocessing-1.1.1.dist-info/WHEEL
Keras_Preprocessing-1.1.1.dist-info/top_level.txt
Keras_Preprocessing-1.1.1.dist-info/RECORD
