Metadata-Version: 1.1
Name: Keras_Preprocessing
Version: 1.1.1
Summary: Easy data preprocessing and data augmentation for deep learning models
Home-page: https://github.com/keras-team/keras-preprocessing
Author: Keras Team
Author-email: UNKNOWN
License: MIT
Download-URL: https://github.com/keras-team/keras-preprocessing/tarball/1.1.1
Platform: UNKNOWN
Classifier: Development Status :: 5 - Production/Stable
Classifier: Intended Audience :: Developers
Classifier: Intended Audience :: Education
Classifier: Intended Audience :: Science/Research
Classifier: License :: OSI Approved :: MIT License
Classifier: Programming Language :: Python :: 2
Classifier: Programming Language :: Python :: 2.7
Classifier: Programming Language :: Python :: 3
Classifier: Programming Language :: Python :: 3.6
Classifier: Topic :: Software Development :: Libraries
Classifier: Topic :: Software Development :: Libraries :: Python Modules
